aunnl/__init__.py
aunnl-3.0.3.dist-info/LICENSE
aunnl-3.0.3.dist-info/METADATA
aunnl-3.0.3.dist-info/WHEEL
aunnl-3.0.3.dist-info/top_level.txt
aunnl-3.0.3.dist-info/RECORD
