Metadata-Version: 2.1
Name: aunnl
Version: 3.0.3
Summary: Another Unnecessary Neural Network Library
Home-page: https://github.com/adityaradk/aunnl
Author: Aditya Radhakrishnan
Author-email: adityaradk@gmail.com
License: MIT
Keywords: Deep Learning,Machine Learning,Artificial Neural Networks
Platform: UNKNOWN
Requires-Dist: numpy
Requires-Dist: scipy
